odoo8_addon_website_snippet_marginless_gallery-8.0.1.0.1.99.dev16-py2.7-nspkg.pth
odoo8_addon_website_snippet_marginless_gallery-8.0.1.0.1.99.dev16.dist-info/METADATA
odoo8_addon_website_snippet_marginless_gallery-8.0.1.0.1.99.dev16.dist-info/RECORD
odoo8_addon_website_snippet_marginless_gallery-8.0.1.0.1.99.dev16.dist-info/WHEEL
odoo8_addon_website_snippet_marginless_gallery-8.0.1.0.1.99.dev16.dist-info/namespace_packages.txt
odoo8_addon_website_snippet_marginless_gallery-8.0.1.0.1.99.dev16.dist-info/top_level.txt
odoo_addons/website_snippet_marginless_gallery/README.rst
odoo_addons/website_snippet_marginless_gallery/__init__.py
odoo_addons/website_snippet_marginless_gallery/__openerp__.py
odoo_addons/website_snippet_marginless_gallery/i18n/de.po
odoo_addons/website_snippet_marginless_gallery/i18n/es.po
odoo_addons/website_snippet_marginless_gallery/i18n/fr.po
odoo_addons/website_snippet_marginless_gallery/i18n/it.po
odoo_addons/website_snippet_marginless_gallery/i18n/pt_BR.po
odoo_addons/website_snippet_marginless_gallery/i18n/ru.po
odoo_addons/website_snippet_marginless_gallery/i18n/sl.po
odoo_addons/website_snippet_marginless_gallery/i18n/website_snippet_marginless_gallery.pot
odoo_addons/website_snippet_marginless_gallery/images/marginless_gallery.png
odoo_addons/website_snippet_marginless_gallery/static/description/icon.png
odoo_addons/website_snippet_marginless_gallery/static/description/icon.svg
odoo_addons/website_snippet_marginless_gallery/static/src/css/website_snippet_marginless_gallery.css
odoo_addons/website_snippet_marginless_gallery/static/src/css/website_snippet_marginless_gallery.css.map
odoo_addons/website_snippet_marginless_gallery/static/src/css/website_snippet_marginless_gallery.sass
odoo_addons/website_snippet_marginless_gallery/static/src/js/website_snippet_marginless_gallery.editor.js
odoo_addons/website_snippet_marginless_gallery/static/src/js/website_snippet_marginless_gallery.tour.js
odoo_addons/website_snippet_marginless_gallery/tests/__init__.py
odoo_addons/website_snippet_marginless_gallery/tests/test_ui.py
odoo_addons/website_snippet_marginless_gallery/views/assets.xml
odoo_addons/website_snippet_marginless_gallery/views/snippets.xml
