Metadata-Version: 2.1
Name: odoo8-addon-website-snippet-marginless-gallery
Version: 8.0.1.0.1.99.dev16
Summary: Add a snippet to have a marginless image gallery
Home-page: https://odoo-community.org/project/website-maintainers-79
Author: Grupo ESOC Ingeniería de Servicios, Odoo Community Association (OCA)
Author-email: support@odoo-community.org
License: AGPL-3
Platform: UNKNOWN
Classifier: Programming Language :: Python
Classifier: Framework :: Odoo
Classifier: License :: OSI Approved :: GNU Affero General Public License v3
Requires-Python: ~=2.7
Requires-Dist: odoo (<9.0a,>=8.0a)
